oc_log_helper/__init__.py
oc_log_helper/add_toggl_entry.py
oc_log_helper/main.py
oc_log_helper/start_toggl_tracking.py
oc_log_helper-0.0.2.dist-info/entry_points.txt
oc_log_helper-0.0.2.dist-info/LICENSE
oc_log_helper-0.0.2.dist-info/WHEEL
oc_log_helper-0.0.2.dist-info/METADATA
oc_log_helper-0.0.2.dist-info/RECORD
