Metadata-Version: 2.1
Name: oc_log_helper
Version: 0.0.2
Summary: Let's build a new CLI application.
Author-email: 0x29a <nk0d6bxt@anonaddy.me>
Requires-Python: >=3.8
Classifier: License :: OSI Approved :: GNU General Public License v3 or later (GPLv3+)
Requires-Dist: click==8.0.3
Requires-Dist: pendulum==2.1.2
Requires-Dist: togglCli==2.4.3
Project-URL: Home, https://github.com/0x29a/oc_log_helper
